dns_mollusc/__init__.py
dns_mollusc/client.py
dns_mollusc/response.py
dns_mollusc-0.2.dist-info/LICENSE
dns_mollusc-0.2.dist-info/METADATA
dns_mollusc-0.2.dist-info/WHEEL
dns_mollusc-0.2.dist-info/top_level.txt
dns_mollusc-0.2.dist-info/RECORD
