Metadata-Version: 2.1
Name: dns-mollusc
Version: 0.2
Summary: A simple, synchronous, rate-limiting DoH client to check if a given response is filtered by the specified resolver.
Home-page: https://chris.partridge.tech/
Author: Chris Partridge
Author-email: tweedge-public@partridge.tech
License: Apache License 2.0
Project-URL: Source, https://github.com/tweedge/dns-mollusc
Classifier: Development Status :: 4 - Beta
Classifier: License :: OSI Approved :: Apache Software License
Classifier: Operating System :: MacOS
Classifier: Operating System :: Microsoft :: Windows
Classifier: Operating System :: POSIX :: Linux
Classifier: Programming Language :: Python
Classifier: Programming Language :: Python :: 3
Classifier: Programming Language :: Python :: 3.7
Classifier: Programming Language :: Python :: 3.8
Classifier: Programming Language :: Python :: 3.9
Classifier: Programming Language :: Python :: 3.10
License-File: LICENSE
Requires-Dist: requests
